jinjax_ui/__init__.py
jinjax_ui/ui/alert/actions.jinja
jinjax_ui/ui/alert/alert.css
jinjax_ui/ui/alert/alert.js
jinjax_ui/ui/alert/description.jinja
jinjax_ui/ui/alert/index.jinja
jinjax_ui/ui/avatar/avatar.css
jinjax_ui/ui/avatar/group.jinja
jinjax_ui/ui/avatar/index.jinja
jinjax_ui/ui/badge.css
jinjax_ui/ui/badge.jinja
jinjax_ui/ui/button.css
jinjax_ui/ui/button.jinja
jinjax_ui/ui/checkbox.css
jinjax_ui/ui/checkbox.jinja
jinjax_ui/ui/details/details.css
jinjax_ui/ui/details/index.jinja
jinjax_ui/ui/details/panel.jinja
jinjax_ui/ui/details/summary.jinja
jinjax_ui/ui/dialog/dialog.js
jinjax_ui/ui/dialog/footer.jinja
jinjax_ui/ui/dialog/index.jinja
jinjax_ui/ui/dialog/title.jinja
jinjax_ui/ui/form/caption.jinja
jinjax_ui/ui/form/counter.jinja
jinjax_ui/ui/form/counter.js
jinjax_ui/ui/form/field.css
jinjax_ui/ui/form/field.jinja
jinjax_ui/ui/form/footer.jinja
jinjax_ui/ui/form/label.jinja
jinjax_ui/ui/form/loading.jinja
jinjax_ui/ui/form/wrapper.jinja
jinjax_ui/ui/globals.jinja
jinjax_ui/ui/icon.css
jinjax_ui/ui/icon.jinja
jinjax_ui/ui/input.css
jinjax_ui/ui/input.jinja
jinjax_ui/ui/jxui.css
jinjax_ui/ui/linked-list.css
jinjax_ui/ui/linked-list.jinja
jinjax_ui/ui/linked-list.js
jinjax_ui/ui/material-symbols-rounded.woff2
jinjax_ui/ui/menu/button.jinja
jinjax_ui/ui/menu/index.jinja
jinjax_ui/ui/menu/item-sub.jinja
jinjax_ui/ui/menu/item.jinja
jinjax_ui/ui/menu/menu.js
jinjax_ui/ui/panel.css
jinjax_ui/ui/panel.jinja
jinjax_ui/ui/popover.css
jinjax_ui/ui/popover.jinja
jinjax_ui/ui/popover.js
jinjax_ui/ui/radio.css
jinjax_ui/ui/radio.jinja
jinjax_ui/ui/select.css
jinjax_ui/ui/select.jinja
jinjax_ui/ui/stimulus.js
jinjax_ui/ui/tab/group.jinja
jinjax_ui/ui/tab/index.jinja
jinjax_ui/ui/tab/list.jinja
jinjax_ui/ui/tab/option.jinja
jinjax_ui/ui/tab/panel.jinja
jinjax_ui/ui/tab/select.jinja
jinjax_ui/ui/tab/tab.css
jinjax_ui/ui/tab/tab.js
jinjax_ui/ui/table.css
jinjax_ui/ui/table.jinja
jinjax_ui/ui/textarea.jinja
jinjax_ui/ui/time-ago.jinja
jinjax_ui/ui/time-ago.js
jinjax_ui-1.1.8.dist-info/METADATA
jinjax_ui-1.1.8.dist-info/WHEEL
jinjax_ui-1.1.8.dist-info/entry_points.txt
jinjax_ui-1.1.8.dist-info/RECORD
