Metadata-Version: 2.3
Name: jinjax-ui
Version: 1.1.8
Summary: JinjaX UI components
Author: Juan Pablo Scaletti
Author-email: juanpablo@jpscaletti.com
Requires-Python: >=3.11,<4
Classifier: Development Status :: 4 - Beta
Classifier: Environment :: Web Environment
Classifier: Intended Audience :: Developers
Classifier: Programming Language :: Python :: 3 :: Only
Classifier: Programming Language :: Python :: 3.11
Classifier: Programming Language :: Python :: 3.12
Classifier: Programming Language :: Python :: 3.13
Classifier: Programming Language :: Python :: 3.14
Classifier: Topic :: Internet :: WWW/HTTP :: Dynamic Content
Classifier: Topic :: Software Development :: Libraries
Classifier: Topic :: Software Development :: Libraries :: Python Modules
Classifier: Topic :: Software Development :: User Interfaces
Classifier: Topic :: Text Processing :: Markup :: HTML
Requires-Dist: jinjax (>=0.56)
Project-URL: Documentation, https://jxui.scaletti.dev/
Project-URL: Homepage, https://jxui.scaletti.dev/
Project-URL: Repository, https://github.com/jpsca/jinjax-ui
